objective/__init__.py
objective/_base_client.py
objective/_client.py
objective/_compat.py
objective/_constants.py
objective/_exceptions.py
objective/_files.py
objective/_models.py
objective/_qs.py
objective/_resource.py
objective/_response.py
objective/_streaming.py
objective/_types.py
objective/_version.py
objective/py.typed
objective/_utils/__init__.py
objective/_utils/_logs.py
objective/_utils/_proxy.py
objective/_utils/_reflection.py
objective/_utils/_streams.py
objective/_utils/_sync.py
objective/_utils/_transform.py
objective/_utils/_typing.py
objective/_utils/_utils.py
objective/lib/.keep
objective/lib/cli.py
objective/resources/__init__.py
objective/resources/indexes.py
objective/resources/objects.py
objective/types/__init__.py
objective/types/index_create_params.py
objective/types/index_create_response.py
objective/types/index_delete_response.py
objective/types/index_finetune_params.py
objective/types/index_finetune_response.py
objective/types/index_get_response.py
objective/types/index_list_response.py
objective/types/index_search_params.py
objective/types/index_search_response.py
objective/types/index_status_by_type_response.py
objective/types/index_status_response.py
objective/types/object_batch_params.py
objective/types/object_batch_response.py
objective/types/object_create_params.py
objective/types/object_create_response.py
objective/types/object_delete_all_response.py
objective/types/object_delete_response.py
objective/types/object_get_response.py
objective/types/object_list_params.py
objective/types/object_list_response.py
objective/types/object_status_response.py
objective/types/object_update_params.py
objective/types/object_update_response.py
objective_sdk-5.22.0.dist-info/METADATA
objective_sdk-5.22.0.dist-info/WHEEL
objective_sdk-5.22.0.dist-info/entry_points.txt
objective_sdk-5.22.0.dist-info/licenses/LICENSE
objective_sdk-5.22.0.dist-info/RECORD
